code_payload/__init__.py
code_payload/cli.py
code_payload/config.py
code_payload/core.py
code_payload/default_config.yaml
code_payload/file_handling.py
code_payload/main.py
code_payload/models.py
code_payload/summarization.py
code_payload/template_rendering.py
code_payload/templates/default.j2
code_payload/templates/html_report.j2
code_payload/templates/python_dev.j2
code_payload/templates/readme_summary.j2
code_payload-0.1.8.dist-info/METADATA
code_payload-0.1.8.dist-info/WHEEL
code_payload-0.1.8.dist-info/entry_points.txt
code_payload-0.1.8.dist-info/licenses/LICENSE
code_payload-0.1.8.dist-info/RECORD
