Metadata-Version: 2.3
Name: code-payload
Version: 0.1.8
Summary: Giving language models context of your codebase
Project-URL: Homepage, https://github.com/darth-veitcher/code-payload
Project-URL: Source, https://github.com/darth-veitcher/code-payload
Project-URL: Issues, https://github.com/darth-veitcher/code-payload/issues
Project-URL: Documentation, https://github.com/darth-veitcher/code-payload
Author-email: darth-veitcher <1722315+darth-veitcher@users.noreply.github.com>
License: MIT License
License-File: LICENSE
Requires-Python: >=3.8
Requires-Dist: chardet>=5.2.0
Requires-Dist: hatch-fancy-pypi-readme>=24.1.0
Requires-Dist: jinja2>=3.1.4
Requires-Dist: omegaconf>=2.3.0
Requires-Dist: pydantic>=2.8.2
Requires-Dist: rich>=13.8.0
Requires-Dist: tiktoken>=0.7.0
Requires-Dist: typer>=0.12.5
Provides-Extra: docs
Requires-Dist: mkdocs-gen-files>=0.5.0; extra == 'docs'
Requires-Dist: mkdocs-literate-nav>=0.6.1; extra == 'docs'
Requires-Dist: mkdocs-material>=9.5.34; extra == 'docs'
Requires-Dist: mkdocs-section-index>=0.3.9; extra == 'docs'
Requires-Dist: mkdocs>=1.6.1; extra == 'docs'
Requires-Dist: mkdocstrings[python]>=0.26.0; extra == 'docs'
